powerstrip/__init__.py
powerstrip/exceptions.py
powerstrip/pluginmanager.py
powerstrip/cerberusutils/__init__.py
powerstrip/cerberusutils/customvalidator.py
powerstrip/cerberusutils/schema/__init__.py
powerstrip/cerberusutils/schema/pluginmetadata.py
powerstrip/models/__init__.py
powerstrip/models/metadata.py
powerstrip/models/plugin.py
powerstrip/models/pluginpackage.py
powerstrip/utils/__init__.py
powerstrip/utils/module.py
powerstrip/utils/semver.py
powerstrip/utils/utils.py
python_powerstrip-0.0.7.dist-info/LICENSE
python_powerstrip-0.0.7.dist-info/METADATA
python_powerstrip-0.0.7.dist-info/WHEEL
python_powerstrip-0.0.7.dist-info/top_level.txt
python_powerstrip-0.0.7.dist-info/RECORD
