Metadata-Version: 2.1
Name: python-powerstrip
Version: 0.0.7
Summary: Simple module to manage plugins.
Home-page: https://github.com/keans/powerstrip
Author: Ansgar Kellner
Author-email: keans@gmx.de
License: MIT
Keywords: powerstrip
Platform: UNKNOWN
Classifier: Development Status :: 3 - Alpha
Classifier: Intended Audience :: Developers
Classifier: Topic :: Software Development :: Build Tools
Classifier: License :: OSI Approved :: MIT License
Classifier: Programming Language :: Python :: 3
Classifier: Programming Language :: Python :: 3.6
Classifier: Programming Language :: Python :: 3.7
Classifier: Programming Language :: Python :: 3.8
Classifier: Programming Language :: Python :: 3.9
Classifier: Programming Language :: Python :: 3.10
Requires-Python: >=3.6
License-File: LICENSE
Requires-Dist: pyyaml
Requires-Dist: cerberus
